Metadata-Version: 2.1
Name: datachisel
Version: 1.0
Summary: an easy way to store data and load them in files
Author: LeoDev (COSMICDEV)
